twinthread/__init__.py
twinthread/dataset
twinthread/datasetx
twinthread/exec_task.py
twinthread/jupyter.py
twinthread/something_else
twinthread/string_handling.py
twinthread/testing.py
twinthread-1.5.0.dist-info/METADATA
twinthread-1.5.0.dist-info/WHEEL
twinthread-1.5.0.dist-info/RECORD
