Metadata-Version: 2.1
Name: twinthread
Version: 1.5.0
Summary: 
Author: Brent Baumgartner
Requires-Python: >=3.12,<3.13
Classifier: Programming Language :: Python :: 3
Requires-Dist: azure-storage-blob (>=12.13.0,<13.0.0)
Requires-Dist: matplotlib (>=3.7.0,<4.0.0)
Requires-Dist: pandas (==2.2.2)
Requires-Dist: plotly (>=4.8.1,<5.0.0)
Requires-Dist: requests (>=2.31.0,<3.0.0)
Requires-Dist: requests_toolbelt (>=1.0.0,<2.0.0)
Requires-Dist: simplejson (>=3.17.0,<4.0.0)
Requires-Dist: urllib3 (>=2.5.0,<3.0.0)
